odoo/addons/product_attribute_model_link/README.rst
odoo/addons/product_attribute_model_link/__init__.py
odoo/addons/product_attribute_model_link/__manifest__.py
odoo/addons/product_attribute_model_link/i18n/es.po
odoo/addons/product_attribute_model_link/i18n/it.po
odoo/addons/product_attribute_model_link/i18n/product_attribute_model_link.pot
odoo/addons/product_attribute_model_link/models/__init__.py
odoo/addons/product_attribute_model_link/models/product_attribute.py
odoo/addons/product_attribute_model_link/models/product_attribute_value.py
odoo/addons/product_attribute_model_link/readme/CONFIGURE.rst
odoo/addons/product_attribute_model_link/readme/CONTEXT.rst
odoo/addons/product_attribute_model_link/readme/CONTRIBUTORS.rst
odoo/addons/product_attribute_model_link/readme/DESCRIPTION.rst
odoo/addons/product_attribute_model_link/readme/USAGE.rst
odoo/addons/product_attribute_model_link/security/ir.model.access.csv
odoo/addons/product_attribute_model_link/static/description/icon.png
odoo/addons/product_attribute_model_link/static/description/index.html
odoo/addons/product_attribute_model_link/tests/__init__.py
odoo/addons/product_attribute_model_link/tests/test_product_attribute_model_link.py
odoo/addons/product_attribute_model_link/views/product_attribute_views.xml
odoo/addons/product_attribute_model_link/wizards/__init__.py
odoo/addons/product_attribute_model_link/wizards/linked_record_wizard.py
odoo/addons/product_attribute_model_link/wizards/linked_record_wizard_view.xml
odoo_addon_product_attribute_model_link-16.0.1.0.1.2.dist-info/METADATA
odoo_addon_product_attribute_model_link-16.0.1.0.1.2.dist-info/WHEEL
odoo_addon_product_attribute_model_link-16.0.1.0.1.2.dist-info/top_level.txt
odoo_addon_product_attribute_model_link-16.0.1.0.1.2.dist-info/RECORD
