Metadata-Version: 2.1
Name: odoo-addon-product-attribute-model-link
Version: 16.0.1.0.1.2
Summary: Use any model records as product attribute values
Home-page: https://github.com/OCA/product-attribute
Author: Cetmix, Odoo Community Association (OCA)
Author-email: support@odoo-community.org
License: AGPL-3
Platform: UNKNOWN
Classifier: Programming Language :: Python
Classifier: Framework :: Odoo
Classifier: Framework :: Odoo :: 16.0
Classifier: License :: OSI Approved :: GNU Affero General Public License v3
Requires-Python: >=3.10
Requires-Dist: odoo-addon-product-attribute-archive <16.1dev,>=16.0dev
Requires-Dist: odoo <16.1dev,>=16.0a
